<?xml version="1.0" encoding="utf-8"?><enquiryDocument xmlns:xsi="http://www.w3.org/2001/XMLSchema-instance" xmlns:xs="http://www.w3.org/2001/XMLSchema" schemaVersion="32.0.0" version="1.0.0" xmlns="http://www.e-mis.com/emisopen"><id>6f13be72-0a4c-4776-8b84-5b947ae55777</id><creationTime>2023-03-27T11:11:25.4951668+01:00</creationTime><report><id>bda3a0fd-40eb-4e98-a119-2296496d966b</id><name>psoriasis</name><description /><creationTime>2019-10-31T14:15:19.6108469+00:00</creationTime><author><userInRole>a173269f-2137-4e33-8a77-bbfe0ccd96d6</userInRole></author><populationType>PATIENT</populationType><folder>2b8b6e42-21a2-4aac-a936-bc82448762da</folder><parent parentType="ACTIVE" /><searchDate>BASELINE</searchDate><population><criteriaGroup><definition><memberOperator>AND</memberOperator><criteria><criterion><id>09241cb7-2560-418c-b807-a656fb56c00c</id><table>EVENTS</table><displayName>Clinical Codes</displayName><negation>false</negation><filterAttribute><columnValue><id>88b55d3e-94ed-4815-929f-5024ada126ee</id><column>READCODE</column><displayName>Clinical Code</displayName><inNotIn>IN</inNotIn><valueSet><id>0c25ceba-8c31-4cba-811f-ecb03a10db4b</id><codeSystem>SCT_READV2</codeSystem><values><value>308725015</value><displayName>Psoriasis and similar disorders</displayName><includeChildren>true</includeChildren><legacyValue>M16</legacyValue></values><values><value>308776017</value><displayName>Psoriasis and similar disorders NOS</displayName><includeChildren>true</includeChildren><legacyValue>M16z</legacyValue></values><values><value>308775018</value><displayName>Other psoriasis and similar disorders</displayName><includeChildren>true</includeChildren><legacyValue>M16y</legacyValue></values><values><value>308731017</value><displayName>Other psoriasis</displayName><includeChildren>true</includeChildren><legacyValue>M161</legacyValue></values><values><value>309331014</value><displayName>[X]Other psoriasis</displayName><includeChildren>true</includeChildren><legacyValue>Myu30</legacyValue></values><values><value>308732012</value><displayName>Psoriasis unspecified</displayName><includeChildren>true</includeChildren><legacyValue>M1610</legacyValue></values><values><value>308733019</value><displayName>Psoriasis annularis</displayName><includeChildren>true</includeChildren><legacyValue>M1611</legacyValue></values><values><value>308734013</value><displayName>Psoriasis circinata</displayName><includeChildren>true</includeChildren><legacyValue>M1612</legacyValue></values><values><value>308735014</value><displayName>Psoriasis diffusa</displayName><includeChildren>true</includeChildren><legacyValue>M1613</legacyValue></values><values><value>198791000006112</value><displayName>Psoriasis discoidea</displayName><includeChildren>true</includeChildren><legacyValue>M1614</legacyValue></values><values><value>308739015</value><displayName>Psoriasis geographica</displayName><includeChildren>true</includeChildren><legacyValue>M1615</legacyValue></values><values><value>61797015</value><displayName>Guttate psoriasis</displayName><includeChildren>true</includeChildren><legacyValue>M1616</legacyValue></values><values><value>308740018</value><displayName>Psoriasis gyrata</displayName><includeChildren>true</includeChildren><legacyValue>M1617</legacyValue></values><values><value>308741019</value><displayName>Psoriasis inveterata</displayName><includeChildren>true</includeChildren><legacyValue>M1618</legacyValue></values><values><value>198841000006110</value><displayName>Psoriasis ostracea</displayName><includeChildren>true</includeChildren><legacyValue>M1619</legacyValue></values><values><value>308744010</value><displayName>Psoriasis palmaris</displayName><includeChildren>true</includeChildren><legacyValue>M161A</legacyValue></values><values><value>308745011</value><displayName>Psoriasis plantaris</displayName><includeChildren>true</includeChildren><legacyValue>M161B</legacyValue></values><values><value>308746012</value><displayName>Psoriasis punctata</displayName><includeChildren>true</includeChildren><legacyValue>M161C</legacyValue></values><values><value>308749017</value><displayName>Psoriasis universalis</displayName><includeChildren>true</includeChildren><legacyValue>M161E</legacyValue></values><values><value>308750017</value><displayName>Psoriasis vulgaris</displayName><includeChildren>true</includeChildren><legacyValue>M161F</legacyValue></values><values><value>1629311000006117</value><displayName>Chronic large plaque psoriasis</displayName><includeChildren>true</includeChildren><legacyValue>M161F-1</legacyValue></values><values><value>1583831000006118</value><displayName>Chronic large plaque psoriasis</displayName><includeChildren>true</includeChildren><legacyValue>EMISNQCH31</legacyValue></values><values><value>308752013</value><displayName>Erythrodermic psoriasis</displayName><includeChildren>true</includeChildren><legacyValue>M161H</legacyValue></values><values><value>308753015</value><displayName>Psoriasis NOS</displayName><includeChildren>true</includeChildren><legacyValue>M161z</legacyValue></values><values><value>357623013</value><displayName>Scalp psoriasis</displayName><includeChildren>true</includeChildren><legacyValue>M16y0</legacyValue></values></valueSet></columnValue><columnValue><id>4930e061-ef20-4278-a5e6-ee5e59e2a058</id><column>DATE</column><displayName>Date</displayName><inNotIn>IN</inNotIn><rangeValue><rangeTo><value><value>0</value><unit>DATE</unit><relation>RELATIVE</relation></value><operator>LTEQ</operator></rangeTo></rangeValue></columnValue></filterAttribute></criterion></criteria></definition><actionIfTrue>SELECT</actionIfTrue><actionIfFalse>REJECT</actionIfFalse><id>87029066-9c5f-4ee0-a71a-e60b6fd50e2a</id></criteriaGroup></population></report></enquiryDocument>